LICENSE
MANIFEST.in
README.md
requirements.txt
rightscalerc.example
setup.cfg
setup.py
version.txt
python_rightscale.egg-info/PKG-INFO
python_rightscale.egg-info/SOURCES.txt
python_rightscale.egg-info/dependency_links.txt
python_rightscale.egg-info/requires.txt
python_rightscale.egg-info/top_level.txt
rightscale/__init__.py
rightscale/actions.py
rightscale/commands.py
rightscale/httpclient.py
rightscale/rightscale.py
rightscale/util.py