Metadata-Version: 1.0
Name: python-rightscale
Version: 0.1.3
Summary: Python wrapper for the Rightscale API
Home-page: https://github.com/brantai/python-rightscale
Author: Brent Naylor
Author-email: brantai@gmail.com
License: MIT
Platform: UNKNOWN
